zwpy/__init__.py
zwpy/zwpy.py
idev_zwpy-1.0.0.dist-info/LICENSE
idev_zwpy-1.0.0.dist-info/METADATA
idev_zwpy-1.0.0.dist-info/WHEEL
idev_zwpy-1.0.0.dist-info/entry_points.txt
idev_zwpy-1.0.0.dist-info/top_level.txt
idev_zwpy-1.0.0.dist-info/RECORD
