Metadata-Version: 2.1
Name: idev-zwpy
Version: 1.0.0
Summary: A python script for hiding secret text into public text utilizing zero-width encoding.
Home-page: https://github.com/IrtsaDevelopment/zwpy
Author: IrtsaDevelopment
Author-email: Irtsa <irtsa.development@gmail.com>
Project-URL: Homepage, https://github.com/IrtsaDevelopment/zwpy
Project-URL: Bug Tracker, https://github.com/IrtsaDevelopment/zwpy/issues
Classifier: Programming Language :: Python :: 3
Classifier: License :: OSI Approved :: MIT License
Classifier: Operating System :: OS Independent
Requires-Python: >=3.6
License-File: LICENSE
Requires-Dist: idev-pytermcolor
